LICENSE
MANIFEST.in
README.rst
setup.py
configuration/__init__.py
configuration/admin.py
configuration/models.py
configuration/templatetags/__init__.py
configuration/templatetags/configuration.py
django_configuration.egg-info/PKG-INFO
django_configuration.egg-info/SOURCES.txt
django_configuration.egg-info/dependency_links.txt
django_configuration.egg-info/requires.txt
django_configuration.egg-info/top_level.txt