Metadata-Version: 1.0
Name: django-configuration
Version: 0.0.3
Summary: Configuration admin/models for Django.
Home-page: https://github.com/fah-designs/django-configuration
Author: Richard Ward
Author-email: richard.ward@fah-designs.co.uk
License: MIT
Platform: UNKNOWN
